bfactory.py
bfactory/__init__.py
bfactory/main.py
bfactory/cli/__init__.py
bfactory/cli/django_cli.py
bfactory/config/__init__.py
bfactory/config/settings.py
bfactory/core/__init__.py
bfactory/core/engine.py
bfactory/core/tasks.py
bfactory/core/templates/READ.ME
bfactory/core/templates/admin.py
bfactory/core/templates/models.py
bfactory/core/templates/myconf.py
bfactory/core/templates/selectors.py
bfactory/core/templates/services.py
bfactory/core/templates/urls.py
bfactory/core/templates/views.py
bfactory/core/templates/helpers/field.py
bfactory/core/templates/helpers/field_serializer.py
bfactory/core/templates/helpers/field_type_linting.py
bfactory/inputs/__init__.py
bfactory/inputs/arguments.py
bfactory/inputs/manifest.py
bfactory/inputs/manifest.schema.json
bfactory/inputs/parse_manifest.py
bfactory/inputs/validators.py
bfactory/tests/__init__.py
bfactory/tests/engine_tests.py
bfactory/tests/jsonschema_test.py
bfactory/tests/manifest_test.json
bfactory/tests/manifest_test.py
bfactory/tests/run_tests.py
bfactory/utils/crypto.py
bfactory/utils/render.py
bfactory/utils/state.py
bfactory-0.4.4.dist-info/LICENSE
bfactory-0.4.4.dist-info/METADATA
bfactory-0.4.4.dist-info/WHEEL
bfactory-0.4.4.dist-info/entry_points.txt
bfactory-0.4.4.dist-info/top_level.txt
bfactory-0.4.4.dist-info/RECORD
