Metadata-Version: 2.1
Name: bfactory
Version: 0.4.4
Summary: Build an API from a manifest file
Home-page: https://github.com/forkear/bfactory
Author: Forkear
Author-email: forkear@no-spam.org
Project-URL: Documentation, https://github.com/forkear/bfactory/blob/main/README.md
Project-URL: Source, https://github.com/forkear/bfactory
Project-URL: Tracker, https://github.com/forkear/bfactory/issues
Requires-Python: >=3.8
License-File: LICENSE
Requires-Dist: Django (==4.2)
Requires-Dist: djangorestframework (==3.14.0)
Requires-Dist: djangorestframework-simplejwt (==5.2.2)
Requires-Dist: Jinja2 (==3.1.2)
